{
  "product_line": "KubeDB",
  "release": "v2020.10.27-rc.2",
  "release_date": "2020-10-27T22:14:25.606886388Z",
  "release_project_url": "https://github.com/kubedb/CHANGELOG",
  "docs_url": "https://kubedb.com/docs/v2020.10.27-rc.2",
  "kubernetes_version": "1.12+",
  "projects": [
    {
      "url": "github.com/kubedb/apimachinery",
      "releases": [
        {
          "tag": "v0.14.0-rc.2",
          "commits": [
            {
              "SHA": "dbc93cda",
              "Subject": "Add dnsConfig and dnsPolicy to podTemplate (#636)"
            }
          ]
        }
      ]
    },
    {
      "url": "github.com/kubedb/cli",
      "releases": [
        {
          "tag": "v0.14.0-rc.2",
          "commits": [
            {
              "SHA": "b00a2123",
              "Subject": "Prepare for release v0.14.0-rc.2 (#533)"
            }
          ]
        }
      ]
    },
    {
      "url": "github.com/kubedb/memcached",
      "releases": [
        {
          "tag": "v0.7.0-rc.2",
          "commits": [
            {
              "SHA": "a63e015b",
              "Subject": "Prepare for release v0.7.0-rc.2 (#228)"
            }
          ]
        }
      ]
    },
    {
      "url": "github.com/kubedb/mongodb",
      "releases": [
        {
          "tag": "v0.7.0-rc.2",
          "commits": [
            {
              "SHA": "d87c55bb",
              "Subject": "Prepare for release v0.7.0-rc.2 (#298)"
            }
          ]
        }
      ]
    },
    {
      "url": "github.com/kubedb/mysql",
      "releases": [
        {
          "tag": "v0.7.0-rc.2",
          "commits": [
            {
              "SHA": "921327d1",
              "Subject": "Prepare for release v0.7.0-rc.2 (#288)"
            }
          ]
        }
      ]
    },
    {
      "url": "github.com/kubedb/mysql-replication-mode-detector",
      "releases": [
        {
          "tag": "v0.1.0-rc.2",
          "commits": [
            {
              "SHA": "b49e098",
              "Subject": "Prepare for release v0.1.0-rc.2 (#76)"
            }
          ]
        }
      ]
    },
    {
      "url": "github.com/kubedb/percona-xtradb",
      "releases": [
        {
          "tag": "v0.1.0-rc.2",
          "commits": [
            {
              "SHA": "ae82716f",
              "Subject": "Prepare for release v0.1.0-rc.2 (#120)"
            }
          ]
        }
      ]
    },
    {
      "url": "github.com/kubedb/pg-leader-election",
      "releases": [
        {
          "tag": "v0.2.0-rc.2",
          "commits": null
        }
      ]
    },
    {
      "url": "github.com/kubedb/postgres",
      "releases": [
        {
          "tag": "v0.14.0-rc.2",
          "commits": [
            {
              "SHA": "2ed7a29c",
              "Subject": "Prepare for release v0.14.0-rc.2 (#406)"
            }
          ]
        }
      ]
    },
    {
      "url": "github.com/kubedb/redis",
      "releases": [
        {
          "tag": "v0.7.0-rc.2",
          "commits": [
            {
              "SHA": "ac0d5b08",
              "Subject": "Prepare for release v0.7.0-rc.2 (#247)"
            }
          ]
        }
      ]
    }
  ]
}
